pystruct/__init__.py
pystruct/plot_learning.py
pystruct/datasets/__init__.py
pystruct/datasets/dataset_loaders.py
pystruct/datasets/letters.pickle
pystruct/datasets/scene.pickle
pystruct/datasets/snakes.pickle
pystruct/datasets/synthetic_grids.py
pystruct/inference/__init__.py
pystruct/inference/_viterbi.c
pystruct/inference/_viterbi.pyd
pystruct/inference/common.py
pystruct/inference/inference_methods.py
pystruct/inference/linear_programming.py
pystruct/inference/maxprod.py
pystruct/learners/__init__.py
pystruct/learners/downhill_simplex_ssvm.py
pystruct/learners/frankwolfe_ssvm.py
pystruct/learners/latent_structured_svm.py
pystruct/learners/n_slack_ssvm.py
pystruct/learners/one_slack_ssvm.py
pystruct/learners/ssvm.py
pystruct/learners/structured_perceptron.py
pystruct/learners/subgradient_latent_ssvm.py
pystruct/learners/subgradient_ssvm.py
pystruct/learners/svm.py
pystruct/models/__init__.py
pystruct/models/base.py
pystruct/models/chain_crf.py
pystruct/models/crf.py
pystruct/models/edge_feature_graph_crf.py
pystruct/models/graph_crf.py
pystruct/models/grid_crf.py
pystruct/models/latent_graph_crf.py
pystruct/models/latent_grid_crf.py
pystruct/models/latent_node_crf.py
pystruct/models/multilabel_svm.py
pystruct/models/node_type_edge_feature_graph_crf.py
pystruct/models/setup.py
pystruct/models/typed_crf.py
pystruct/models/unstructured_svm.py
pystruct/models/utils.pyd
pystruct/tests/__init__.py
pystruct/tests/test_datasets.py
pystruct/tests/test_libraries.py
pystruct/tests/test_inference/__init__.py
pystruct/tests/test_inference/test_exact_inference.py
pystruct/tests/test_inference/test_maxprod.py
pystruct/tests/test_learners/__init__.py
pystruct/tests/test_learners/test_binary_svm.py
pystruct/tests/test_learners/test_crammer_singer_svm.py
pystruct/tests/test_learners/test_edge_feature_graph_learning.py
pystruct/tests/test_learners/test_frankwolfe_svm.py
pystruct/tests/test_learners/test_graph_svm.py
pystruct-0.3.2.dist-info/DESCRIPTION.rst
pystruct-0.3.2.dist-info/METADATA
pystruct-0.3.2.dist-info/RECORD
pystruct-0.3.2.dist-info/WHEEL
pystruct-0.3.2.dist-info/metadata.json
pystruct-0.3.2.dist-info/top_level.txt
