Metadata-Version: 2.0
Name: pystruct
Version: 0.3.2
Summary: Structured Learning and Prediction in Python
Home-page: http://pystruct.github.io
Author: Andreas Mueller
Author-email: t3kcit@gmail.com
License: BSD 2-clause
Platform: UNKNOWN
Classifier: Intended Audience :: Science/Research
Classifier: Intended Audience :: Developers
Classifier: License :: OSI Approved
Classifier: Programming Language :: Python
Classifier: Topic :: Scientific/Engineering
Classifier: Operating System :: Microsoft :: Windows
Classifier: Operating System :: POSIX
Classifier: Operating System :: Unix
Classifier: Operating System :: MacOS
Classifier: Programming Language :: Python :: 2
Classifier: Programming Language :: Python :: 2.7
Classifier: Programming Language :: Python :: 3
Classifier: Programming Language :: Python :: 3.6
Requires-Dist: ad3
Requires-Dist: numpy
